{
    "oil_id": "EX00031",
    "adios_data_model_version": "0.11.0",
    "metadata": {
        "name": "Kearl",
        "source_id": "KRLB19Y",
        "reference": {
            "year": 2020,
            "reference": "ExxonMobil\nRefining and Supply Company\n22777 Springwoods Village Parkway,\nSpring, TX 77389\nSource: https://corporate.exxonmobil.com/Crude-oils/Crude-trading/Assays-available-for-download\nAccessed: Dec 9th, 2020"
        },
        "product_type": "Crude Oil NOS",
        "API": 20.2,
        "labels": [
            "Heavy Crude",
            "Medium Crude",
            "Crude Oil"
        ],
        "model_completeness": 68,
        "gnome_suitable": true
    },
    "sub_samples": [
        {
            "metadata": {
                "name": "Fresh Oil Sample",
                "short_name": "Fresh Oil"
            },
            "cut_volume": {
                "value": 100,
                "unit": "%",
                "unit_type": "volumefraction"
            },
            "physical_properties": {
                "pour_point": {
                    "measurement": {
                        "value": -41.993185,
                        "unit": "C",
                        "unit_type": "temperature"
                    }
                },
                "densities": [
                    {
                        "density": {
                            "value": 0.9322,
                            "unit": "g/cm^3",
                            "unit_type": "density"
                        },
                        "ref_temp": {
                            "value": 15.6,
                            "unit": "C",
                            "unit_type": "temperature"
                        }
                    }
                ],
                "kinematic_viscosities": [
                    {
                        "viscosity": {
                            "value": 308.63,
                            "unit": "cSt",
                            "unit_type": "kinematicviscosity"
                        },
                        "ref_temp": {
                            "value": 20.0,
                            "unit": "C",
                            "unit_type": "temperature"
                        }
                    },
                    {
                        "viscosity": {
                            "value": 91.124,
                            "unit": "cSt",
                            "unit_type": "kinematicviscosity"
                        },
                        "ref_temp": {
                            "value": 40.0,
                            "unit": "C",
                            "unit_type": "temperature"
                        }
                    },
                    {
                        "viscosity": {
                            "value": 55.87,
                            "unit": "cSt",
                            "unit_type": "kinematicviscosity"
                        },
                        "ref_temp": {
                            "value": 50.0,
                            "unit": "C",
                            "unit_type": "temperature"
                        }
                    }
                ]
            },
            "distillation_data": {
                "type": "volume fraction",
                "end_point": {
                    "value": 812.17,
                    "unit": "C",
                    "unit_type": "temperature"
                },
                "fraction_recovered": {
                    "value": 1.0,
                    "unit": "fraction",
                    "unit_type": "concentration"
                },
                "cuts": [
                    {
                        "fraction": {
                            "value": 0.0,
                            "unit": "%",
                            "unit_type": "volumefraction"
                        },
                        "vapor_temp": {
                            "value": 7.310699999999997,
                            "unit": "C",
                            "unit_type": "temperature"
                        }
                    },
                    {
                        "fraction": {
                            "value": 5.0,
                            "unit": "%",
                            "unit_type": "volumefraction"
                        },
                        "vapor_temp": {
                            "value": 38.14300000000003,
                            "unit": "C",
                            "unit_type": "temperature"
                        }
                    },
                    {
                        "fraction": {
                            "value": 10.0,
                            "unit": "%",
                            "unit_type": "volumefraction"
                        },
                        "vapor_temp": {
                            "value": 63.249000000000024,
                            "unit": "C",
                            "unit_type": "temperature"
                        }
                    },
                    {
                        "fraction": {
                            "value": 20.0,
                            "unit": "%",
                            "unit_type": "volumefraction"
                        },
                        "vapor_temp": {
                            "value": 214.31,
                            "unit": "C",
                            "unit_type": "temperature"
                        }
                    },
                    {
                        "fraction": {
                            "value": 30.0,
                            "unit": "%",
                            "unit_type": "volumefraction"
                        },
                        "vapor_temp": {
                            "value": 319.34000000000003,
                            "unit": "C",
                            "unit_type": "temperature"
                        }
                    },
                    {
                        "fraction": {
                            "value": 40.0,
                            "unit": "%",
                            "unit_type": "volumefraction"
                        },
                        "vapor_temp": {
                            "value": 382.90999999999997,
                            "unit": "C",
                            "unit_type": "temperature"
                        }
                    },
                    {
                        "fraction": {
                            "value": 50.0,
                            "unit": "%",
                            "unit_type": "volumefraction"
                        },
                        "vapor_temp": {
                            "value": 436.89,
                            "unit": "C",
                            "unit_type": "temperature"
                        }
                    },
                    {
                        "fraction": {
                            "value": 60.0,
                            "unit": "%",
                            "unit_type": "volumefraction"
                        },
                        "vapor_temp": {
                            "value": 492.98,
                            "unit": "C",
                            "unit_type": "temperature"
                        }
                    },
                    {
                        "fraction": {
                            "value": 70.0,
                            "unit": "%",
                            "unit_type": "volumefraction"
                        },
                        "vapor_temp": {
                            "value": 555.82,
                            "unit": "C",
                            "unit_type": "temperature"
                        }
                    },
                    {
                        "fraction": {
                            "value": 80.0,
                            "unit": "%",
                            "unit_type": "volumefraction"
                        },
                        "vapor_temp": {
                            "value": 627,
                            "unit": "C",
                            "unit_type": "temperature"
                        }
                    },
                    {
                        "fraction": {
                            "value": 90.0,
                            "unit": "%",
                            "unit_type": "volumefraction"
                        },
                        "vapor_temp": {
                            "value": 708.92,
                            "unit": "C",
                            "unit_type": "temperature"
                        }
                    },
                    {
                        "fraction": {
                            "value": 95.0,
                            "unit": "%",
                            "unit_type": "volumefraction"
                        },
                        "vapor_temp": {
                            "value": 756.14,
                            "unit": "C",
                            "unit_type": "temperature"
                        }
                    }
                ]
            },
            "bulk_composition": [
                {
                    "name": "Carbon Mass Fraction",
                    "measurement": {
                        "value": 84.46,
                        "unit": "%",
                        "unit_type": "massfraction"
                    }
                },
                {
                    "name": "Hydrogen Mass Fraction",
                    "measurement": {
                        "value": 12.16,
                        "unit": "%",
                        "unit_type": "massfraction"
                    }
                },
                {
                    "name": "Sulfur Mass Fraction",
                    "measurement": {
                        "value": 3.8504,
                        "unit": "%",
                        "unit_type": "massfraction"
                    }
                },
                {
                    "name": "Mercaptan Sulfur Mass Fraction",
                    "measurement": {
                        "value": 68.0,
                        "unit": "ppm",
                        "unit_type": "massfraction"
                    }
                },
                {
                    "name": "Nitrogen Mass Fraction",
                    "measurement": {
                        "value": 3156.3,
                        "unit": "ppm",
                        "unit_type": "massfraction"
                    }
                },
                {
                    "name": "N-Heptane Insolubles (C7 Asphaltenes)",
                    "measurement": {
                        "value": 3.6647,
                        "unit": "%",
                        "unit_type": "massfraction"
                    }
                },
                {
                    "name": "Nickel Mass Fraction",
                    "measurement": {
                        "value": 50.722,
                        "unit": "ppm",
                        "unit_type": "massfraction"
                    }
                },
                {
                    "name": "Vanadium Mass Fraction",
                    "measurement": {
                        "value": 134.26,
                        "unit": "ppm",
                        "unit_type": "massfraction"
                    }
                },
                {
                    "name": "Calcium Mass Fraction",
                    "measurement": {
                        "value": 116.0,
                        "unit": "ppm",
                        "unit_type": "massfraction"
                    }
                },
                {
                    "name": "Hydrogen Sulfide Concentration",
                    "measurement": {
                        "value": 0,
                        "unit": "ppm",
                        "unit_type": "massfraction"
                    }
                },
                {
                    "name": "Salt Content",
                    "measurement": {
                        "value": 0.00122,
                        "unit": "ppm",
                        "unit_type": "massfraction"
                    }
                },
                {
                    "name": "Paraffin Volume Fraction",
                    "measurement": {
                        "value": 22.526,
                        "unit": "%",
                        "unit_type": "massfraction"
                    }
                },
                {
                    "name": "Naphthene Volume Fraction",
                    "measurement": {
                        "value": 21.737,
                        "unit": "%",
                        "unit_type": "massfraction"
                    }
                },
                {
                    "name": "Aromatics (FIA)",
                    "measurement": {
                        "value": 55.719,
                        "unit": "%",
                        "unit_type": "massfraction"
                    }
                }
            ],
            "industry_properties": [
                {
                    "name": "Total Acid Number",
                    "measurement": {
                        "value": 2.0527,
                        "unit": "mg/g",
                        "unit_type": "massfraction"
                    }
                },
                {
                    "name": "Conradson Carbon Residue",
                    "measurement": {
                        "value": 9.0942,
                        "unit": "%",
                        "unit_type": "massfraction"
                    }
                },
                {
                    "name": "Reid Vapor Pressure",
                    "measurement": {
                        "value": 6.83,
                        "unit": "psi",
                        "unit_type": "pressure"
                    }
                }
            ]
        },
        {
            "metadata": {
                "name": "Butane and Lighter IBP - 60F",
                "short_name": "Butane and L...",
                "boiling_point_range": {
                    "unit": "F",
                    "max_value": 60.0,
                    "unit_type": "temperature"
                }
            },
            "cut_volume": {
                "value": 0.772719,
                "unit": "%",
                "unit_type": "volumefraction"
            },
            "physical_properties": {
                "densities": [
                    {
                        "density": {
                            "value": 0.5626,
                            "unit": "g/cm^3",
                            "unit_type": "density"
                        },
                        "ref_temp": {
                            "value": 15.6,
                            "unit": "C",
                            "unit_type": "temperature"
                        }
                    }
                ],
                "kinematic_viscosities": [
                    {
                        "viscosity": {
                            "value": 0.4517,
                            "unit": "cSt",
                            "unit_type": "kinematicviscosity"
                        },
                        "ref_temp": {
                            "value": 20.0,
                            "unit": "C",
                            "unit_type": "temperature"
                        }
                    },
                    {
                        "viscosity": {
                            "value": 0.37883,
                            "unit": "cSt",
                            "unit_type": "kinematicviscosity"
                        },
                        "ref_temp": {
                            "value": 40.0,
                            "unit": "C",
                            "unit_type": "temperature"
                        }
                    },
                    {
                        "viscosity": {
                            "value": 0.35122,
                            "unit": "cSt",
                            "unit_type": "kinematicviscosity"
                        },
                        "ref_temp": {
                            "value": 50.0,
                            "unit": "C",
                            "unit_type": "temperature"
                        }
                    }
                ]
            },
            "distillation_data": {
                "type": "volume fraction",
                "fraction_recovered": {
                    "value": 1.0,
                    "unit": "fraction",
                    "unit_type": "concentration"
                }
            },
            "bulk_composition": [
                {
                    "name": "Carbon Mass Fraction",
                    "measurement": {
                        "value": 82.62,
                        "unit": "%",
                        "unit_type": "massfraction"
                    }
                },
                {
                    "name": "Hydrogen Mass Fraction",
                    "measurement": {
                        "value": 17.38,
                        "unit": "%",
                        "unit_type": "massfraction"
                    }
                },
                {
                    "name": "Sulfur Mass Fraction",
                    "measurement": {
                        "value": 0.0059747,
                        "unit": "%",
                        "unit_type": "massfraction"
                    }
                },
                {
                    "name": "Mercaptan Sulfur Mass Fraction",
                    "measurement": {
                        "value": 30.82,
                        "unit": "ppm",
                        "unit_type": "massfraction"
                    }
                },
                {
                    "name": "Nitrogen Mass Fraction",
                    "measurement": {
                        "value": 0,
                        "unit": "ppm",
                        "unit_type": "massfraction"
                    }
                },
                {
                    "name": "Paraffin Volume Fraction",
                    "measurement": {
                        "value": 99.812,
                        "unit": "%",
                        "unit_type": "massfraction"
                    }
                },
                {
                    "name": "Naphthene Volume Fraction",
                    "measurement": {
                        "value": 0.0,
                        "unit": "%",
                        "unit_type": "massfraction"
                    }
                },
                {
                    "name": "Aromatics (FIA)",
                    "measurement": {
                        "value": 0,
                        "unit": "%",
                        "unit_type": "massfraction"
                    }
                }
            ],
            "industry_properties": [
                {
                    "name": "Total Acid Number",
                    "measurement": {
                        "value": 0.00015586,
                        "unit": "mg/g",
                        "unit_type": "massfraction"
                    }
                }
            ]
        },
        {
            "metadata": {
                "name": "Lt. Naphtha C5 - 165F",
                "short_name": "Lt. Naphtha ...",
                "boiling_point_range": {
                    "unit": "F",
                    "min_value": 60.0,
                    "max_value": 165.0,
                    "unit_type": "temperature"
                }
            },
            "cut_volume": {
                "value": 10.9847,
                "unit": "%",
                "unit_type": "volumefraction"
            },
            "physical_properties": {
                "densities": [
                    {
                        "density": {
                            "value": 0.64123,
                            "unit": "g/cm^3",
                            "unit_type": "density"
                        },
                        "ref_temp": {
                            "value": 15.6,
                            "unit": "C",
                            "unit_type": "temperature"
                        }
                    }
                ],
                "kinematic_viscosities": [
                    {
                        "viscosity": {
                            "value": 0.55856,
                            "unit": "cSt",
                            "unit_type": "kinematicviscosity"
                        },
                        "ref_temp": {
                            "value": 20.0,
                            "unit": "C",
                            "unit_type": "temperature"
                        }
                    },
                    {
                        "viscosity": {
                            "value": 0.4568,
                            "unit": "cSt",
                            "unit_type": "kinematicviscosity"
                        },
                        "ref_temp": {
                            "value": 40.0,
                            "unit": "C",
                            "unit_type": "temperature"
                        }
                    },
                    {
                        "viscosity": {
                            "value": 0.41762,
                            "unit": "cSt",
                            "unit_type": "kinematicviscosity"
                        },
                        "ref_temp": {
                            "value": 50.0,
                            "unit": "C",
                            "unit_type": "temperature"
                        }
                    }
                ]
            },
            "distillation_data": {
                "type": "volume fraction",
                "end_point": {
                    "value": 73.541,
                    "unit": "C",
                    "unit_type": "temperature"
                },
                "fraction_recovered": {
                    "value": 1.0,
                    "unit": "fraction",
                    "unit_type": "concentration"
                },
                "cuts": [
                    {
                        "fraction": {
                            "value": 0.0,
                            "unit": "%",
                            "unit_type": "volumefraction"
                        },
                        "vapor_temp": {
                            "value": 17.10899999999998,
                            "unit": "C",
                            "unit_type": "temperature"
                        }
                    },
                    {
                        "fraction": {
                            "value": 5.0,
                            "unit": "%",
                            "unit_type": "volumefraction"
                        },
                        "vapor_temp": {
                            "value": 21.401999999999987,
                            "unit": "C",
                            "unit_type": "temperature"
                        }
                    },
                    {
                        "fraction": {
                            "value": 10.0,
                            "unit": "%",
                            "unit_type": "volumefraction"
                        },
                        "vapor_temp": {
                            "value": 23.365999999999985,
                            "unit": "C",
                            "unit_type": "temperature"
                        }
                    },
                    {
                        "fraction": {
                            "value": 20.0,
                            "unit": "%",
                            "unit_type": "volumefraction"
                        },
                        "vapor_temp": {
                            "value": 27.12900000000002,
                            "unit": "C",
                            "unit_type": "temperature"
                        }
                    },
                    {
                        "fraction": {
                            "value": 30.0,
                            "unit": "%",
                            "unit_type": "volumefraction"
                        },
                        "vapor_temp": {
                            "value": 35.62900000000002,
                            "unit": "C",
                            "unit_type": "temperature"
                        }
                    },
                    {
                        "fraction": {
                            "value": 40.0,
                            "unit": "%",
                            "unit_type": "volumefraction"
                        },
                        "vapor_temp": {
                            "value": 38.591999999999985,
                            "unit": "C",
                            "unit_type": "temperature"
                        }
                    },
                    {
                        "fraction": {
                            "value": 50.0,
                            "unit": "%",
                            "unit_type": "volumefraction"
                        },
                        "vapor_temp": {
                            "value": 41.442999999999984,
                            "unit": "C",
                            "unit_type": "temperature"
                        }
                    },
                    {
                        "fraction": {
                            "value": 60.0,
                            "unit": "%",
                            "unit_type": "volumefraction"
                        },
                        "vapor_temp": {
                            "value": 44.19200000000001,
                            "unit": "C",
                            "unit_type": "temperature"
                        }
                    },
                    {
                        "fraction": {
                            "value": 70.0,
                            "unit": "%",
                            "unit_type": "volumefraction"
                        },
                        "vapor_temp": {
                            "value": 54.45799999999997,
                            "unit": "C",
                            "unit_type": "temperature"
                        }
                    },
                    {
                        "fraction": {
                            "value": 80.0,
                            "unit": "%",
                            "unit_type": "volumefraction"
                        },
                        "vapor_temp": {
                            "value": 60.721000000000004,
                            "unit": "C",
                            "unit_type": "temperature"
                        }
                    },
                    {
                        "fraction": {
                            "value": 90.0,
                            "unit": "%",
                            "unit_type": "volumefraction"
                        },
                        "vapor_temp": {
                            "value": 67.11199999999997,
                            "unit": "C",
                            "unit_type": "temperature"
                        }
                    },
                    {
                        "fraction": {
                            "value": 95.0,
                            "unit": "%",
                            "unit_type": "volumefraction"
                        },
                        "vapor_temp": {
                            "value": 70.40800000000002,
                            "unit": "C",
                            "unit_type": "temperature"
                        }
                    }
                ]
            },
            "bulk_composition": [
                {
                    "name": "Carbon Mass Fraction",
                    "measurement": {
                        "value": 83.49,
                        "unit": "%",
                        "unit_type": "massfraction"
                    }
                },
                {
                    "name": "Hydrogen Mass Fraction",
                    "measurement": {
                        "value": 16.51,
                        "unit": "%",
                        "unit_type": "massfraction"
                    }
                },
                {
                    "name": "Sulfur Mass Fraction",
                    "measurement": {
                        "value": 0.014275,
                        "unit": "%",
                        "unit_type": "massfraction"
                    }
                },
                {
                    "name": "Mercaptan Sulfur Mass Fraction",
                    "measurement": {
                        "value": 77.26,
                        "unit": "ppm",
                        "unit_type": "massfraction"
                    }
                },
                {
                    "name": "Nitrogen Mass Fraction",
                    "measurement": {
                        "value": 0,
                        "unit": "ppm",
                        "unit_type": "massfraction"
                    }
                },
                {
                    "name": "Paraffin Volume Fraction",
                    "measurement": {
                        "value": 94.846,
                        "unit": "%",
                        "unit_type": "massfraction"
                    }
                },
                {
                    "name": "Naphthene Volume Fraction",
                    "measurement": {
                        "value": 5.0482,
                        "unit": "%",
                        "unit_type": "massfraction"
                    }
                },
                {
                    "name": "Aromatics (FIA)",
                    "measurement": {
                        "value": 0,
                        "unit": "%",
                        "unit_type": "massfraction"
                    }
                }
            ],
            "industry_properties": [
                {
                    "name": "Total Acid Number",
                    "measurement": {
                        "value": 0.0033514,
                        "unit": "mg/g",
                        "unit_type": "massfraction"
                    }
                }
            ]
        },
        {
            "metadata": {
                "name": "Hvy Naphtha 165 - 330F",
                "short_name": "Hvy Naphtha ...",
                "boiling_point_range": {
                    "unit": "F",
                    "min_value": 165.0,
                    "max_value": 330.0,
                    "unit_type": "temperature"
                }
            },
            "cut_volume": {
                "value": 6.29023,
                "unit": "%",
                "unit_type": "volumefraction"
            },
            "physical_properties": {
                "pour_point": {
                    "measurement": {
                        "value": -106.64449,
                        "unit": "C",
                        "unit_type": "temperature"
                    }
                },
                "densities": [
                    {
                        "density": {
                            "value": 0.73415,
                            "unit": "g/cm^3",
                            "unit_type": "density"
                        },
                        "ref_temp": {
                            "value": 15.6,
                            "unit": "C",
                            "unit_type": "temperature"
                        }
                    }
                ],
                "kinematic_viscosities": [
                    {
                        "viscosity": {
                            "value": 0.83463,
                            "unit": "cSt",
                            "unit_type": "kinematicviscosity"
                        },
                        "ref_temp": {
                            "value": 20.0,
                            "unit": "C",
                            "unit_type": "temperature"
                        }
                    },
                    {
                        "viscosity": {
                            "value": 0.65876,
                            "unit": "cSt",
                            "unit_type": "kinematicviscosity"
                        },
                        "ref_temp": {
                            "value": 40.0,
                            "unit": "C",
                            "unit_type": "temperature"
                        }
                    },
                    {
                        "viscosity": {
                            "value": 0.59181,
                            "unit": "cSt",
                            "unit_type": "kinematicviscosity"
                        },
                        "ref_temp": {
                            "value": 50.0,
                            "unit": "C",
                            "unit_type": "temperature"
                        }
                    }
                ]
            },
            "distillation_data": {
                "type": "volume fraction",
                "end_point": {
                    "value": 164.64,
                    "unit": "C",
                    "unit_type": "temperature"
                },
                "fraction_recovered": {
                    "value": 1.0,
                    "unit": "fraction",
                    "unit_type": "concentration"
                },
                "cuts": [
                    {
                        "fraction": {
                            "value": 0.0,
                            "unit": "%",
                            "unit_type": "volumefraction"
                        },
                        "vapor_temp": {
                            "value": 74.08799999999997,
                            "unit": "C",
                            "unit_type": "temperature"
                        }
                    },
                    {
                        "fraction": {
                            "value": 5.0,
                            "unit": "%",
                            "unit_type": "volumefraction"
                        },
                        "vapor_temp": {
                            "value": 75.96500000000003,
                            "unit": "C",
                            "unit_type": "temperature"
                        }
                    },
                    {
                        "fraction": {
                            "value": 10.0,
                            "unit": "%",
                            "unit_type": "volumefraction"
                        },
                        "vapor_temp": {
                            "value": 78.14600000000002,
                            "unit": "C",
                            "unit_type": "temperature"
                        }
                    },
                    {
                        "fraction": {
                            "value": 20.0,
                            "unit": "%",
                            "unit_type": "volumefraction"
                        },
                        "vapor_temp": {
                            "value": 82.77699999999999,
                            "unit": "C",
                            "unit_type": "temperature"
                        }
                    },
                    {
                        "fraction": {
                            "value": 30.0,
                            "unit": "%",
                            "unit_type": "volumefraction"
                        },
                        "vapor_temp": {
                            "value": 87.911,
                            "unit": "C",
                            "unit_type": "temperature"
                        }
                    },
                    {
                        "fraction": {
                            "value": 40.0,
                            "unit": "%",
                            "unit_type": "volumefraction"
                        },
                        "vapor_temp": {
                            "value": 93.70999999999998,
                            "unit": "C",
                            "unit_type": "temperature"
                        }
                    },
                    {
                        "fraction": {
                            "value": 50.0,
                            "unit": "%",
                            "unit_type": "volumefraction"
                        },
                        "vapor_temp": {
                            "value": 100.42000000000002,
                            "unit": "C",
                            "unit_type": "temperature"
                        }
                    },
                    {
                        "fraction": {
                            "value": 60.0,
                            "unit": "%",
                            "unit_type": "volumefraction"
                        },
                        "vapor_temp": {
                            "value": 108.52999999999997,
                            "unit": "C",
                            "unit_type": "temperature"
                        }
                    },
                    {
                        "fraction": {
                            "value": 70.0,
                            "unit": "%",
                            "unit_type": "volumefraction"
                        },
                        "vapor_temp": {
                            "value": 118.54000000000002,
                            "unit": "C",
                            "unit_type": "temperature"
                        }
                    },
                    {
                        "fraction": {
                            "value": 80.0,
                            "unit": "%",
                            "unit_type": "volumefraction"
                        },
                        "vapor_temp": {
                            "value": 131.33000000000004,
                            "unit": "C",
                            "unit_type": "temperature"
                        }
                    },
                    {
                        "fraction": {
                            "value": 90.0,
                            "unit": "%",
                            "unit_type": "volumefraction"
                        },
                        "vapor_temp": {
                            "value": 147.51,
                            "unit": "C",
                            "unit_type": "temperature"
                        }
                    },
                    {
                        "fraction": {
                            "value": 95.0,
                            "unit": "%",
                            "unit_type": "volumefraction"
                        },
                        "vapor_temp": {
                            "value": 156.45,
                            "unit": "C",
                            "unit_type": "temperature"
                        }
                    }
                ]
            },
            "bulk_composition": [
                {
                    "name": "Carbon Mass Fraction",
                    "measurement": {
                        "value": 85.65,
                        "unit": "%",
                        "unit_type": "massfraction"
                    }
                },
                {
                    "name": "Hydrogen Mass Fraction",
                    "measurement": {
                        "value": 14.35,
                        "unit": "%",
                        "unit_type": "massfraction"
                    }
                },
                {
                    "name": "Sulfur Mass Fraction",
                    "measurement": {
                        "value": 0.022142,
                        "unit": "%",
                        "unit_type": "massfraction"
                    }
                },
                {
                    "name": "Mercaptan Sulfur Mass Fraction",
                    "measurement": {
                        "value": 68.58,
                        "unit": "ppm",
                        "unit_type": "massfraction"
                    }
                },
                {
                    "name": "Nitrogen Mass Fraction",
                    "measurement": {
                        "value": 0.0035386,
                        "unit": "ppm",
                        "unit_type": "massfraction"
                    }
                },
                {
                    "name": "Paraffin Volume Fraction",
                    "measurement": {
                        "value": 49.617,
                        "unit": "%",
                        "unit_type": "massfraction"
                    }
                },
                {
                    "name": "Naphthene Volume Fraction",
                    "measurement": {
                        "value": 38.508,
                        "unit": "%",
                        "unit_type": "massfraction"
                    }
                },
                {
                    "name": "Aromatics (FIA)",
                    "measurement": {
                        "value": 11.875,
                        "unit": "%",
                        "unit_type": "massfraction"
                    }
                }
            ],
            "industry_properties": [
                {
                    "name": "Total Acid Number",
                    "measurement": {
                        "value": 0.0312,
                        "unit": "mg/g",
                        "unit_type": "massfraction"
                    }
                },
                {
                    "name": "Freeze Point",
                    "measurement": {
                        "value": -149.671,
                        "unit": "F",
                        "unit_type": "temperature"
                    }
                },
                {
                    "name": "Smoke Point",
                    "measurement": {
                        "value": 32.4746,
                        "unit": "mm",
                        "unit_type": "length"
                    }
                },
                {
                    "name": "Cetane Index 1990 (D4737)",
                    "measurement": {
                        "value": 29.7052,
                        "unit_type": "unitless"
                    }
                },
                {
                    "name": "Cloud Point",
                    "measurement": {
                        "value": -155.369,
                        "unit": "F",
                        "unit_type": "temperature"
                    }
                }
            ]
        },
        {
            "metadata": {
                "name": "Kerosene 330 - 480F",
                "short_name": "Kerosene 330...",
                "boiling_point_range": {
                    "unit": "F",
                    "min_value": 330.0,
                    "max_value": 480.0,
                    "unit_type": "temperature"
                }
            },
            "cut_volume": {
                "value": 4.21528,
                "unit": "%",
                "unit_type": "volumefraction"
            },
            "physical_properties": {
                "pour_point": {
                    "measurement": {
                        "value": -63.288954,
                        "unit": "C",
                        "unit_type": "temperature"
                    }
                },
                "densities": [
                    {
                        "density": {
                            "value": 0.8248,
                            "unit": "g/cm^3",
                            "unit_type": "density"
                        },
                        "ref_temp": {
                            "value": 15.6,
                            "unit": "C",
                            "unit_type": "temperature"
                        }
                    }
                ],
                "kinematic_viscosities": [
                    {
                        "viscosity": {
                            "value": 2.3426,
                            "unit": "cSt",
                            "unit_type": "kinematicviscosity"
                        },
                        "ref_temp": {
                            "value": 20.0,
                            "unit": "C",
                            "unit_type": "temperature"
                        }
                    },
                    {
                        "viscosity": {
                            "value": 1.6176,
                            "unit": "cSt",
                            "unit_type": "kinematicviscosity"
                        },
                        "ref_temp": {
                            "value": 40.0,
                            "unit": "C",
                            "unit_type": "temperature"
                        }
                    },
                    {
                        "viscosity": {
                            "value": 1.3832,
                            "unit": "cSt",
                            "unit_type": "kinematicviscosity"
                        },
                        "ref_temp": {
                            "value": 50.0,
                            "unit": "C",
                            "unit_type": "temperature"
                        }
                    }
                ]
            },
            "distillation_data": {
                "type": "volume fraction",
                "end_point": {
                    "value": 248.62,
                    "unit": "C",
                    "unit_type": "temperature"
                },
                "fraction_recovered": {
                    "value": 1.0,
                    "unit": "fraction",
                    "unit_type": "concentration"
                },
                "cuts": [
                    {
                        "fraction": {
                            "value": 0.0,
                            "unit": "%",
                            "unit_type": "volumefraction"
                        },
                        "vapor_temp": {
                            "value": 166.16999999999996,
                            "unit": "C",
                            "unit_type": "temperature"
                        }
                    },
                    {
                        "fraction": {
                            "value": 5.0,
                            "unit": "%",
                            "unit_type": "volumefraction"
                        },
                        "vapor_temp": {
                            "value": 171.64999999999998,
                            "unit": "C",
                            "unit_type": "temperature"
                        }
                    },
                    {
                        "fraction": {
                            "value": 10.0,
                            "unit": "%",
                            "unit_type": "volumefraction"
                        },
                        "vapor_temp": {
                            "value": 177.65999999999997,
                            "unit": "C",
                            "unit_type": "temperature"
                        }
                    },
                    {
                        "fraction": {
                            "value": 20.0,
                            "unit": "%",
                            "unit_type": "volumefraction"
                        },
                        "vapor_temp": {
                            "value": 189.16999999999996,
                            "unit": "C",
                            "unit_type": "temperature"
                        }
                    },
                    {
                        "fraction": {
                            "value": 30.0,
                            "unit": "%",
                            "unit_type": "volumefraction"
                        },
                        "vapor_temp": {
                            "value": 199.65999999999997,
                            "unit": "C",
                            "unit_type": "temperature"
                        }
                    },
                    {
                        "fraction": {
                            "value": 40.0,
                            "unit": "%",
                            "unit_type": "volumefraction"
                        },
                        "vapor_temp": {
                            "value": 208.97000000000003,
                            "unit": "C",
                            "unit_type": "temperature"
                        }
                    },
                    {
                        "fraction": {
                            "value": 50.0,
                            "unit": "%",
                            "unit_type": "volumefraction"
                        },
                        "vapor_temp": {
                            "value": 217.23000000000002,
                            "unit": "C",
                            "unit_type": "temperature"
                        }
                    },
                    {
                        "fraction": {
                            "value": 60.0,
                            "unit": "%",
                            "unit_type": "volumefraction"
                        },
                        "vapor_temp": {
                            "value": 224.7,
                            "unit": "C",
                            "unit_type": "temperature"
                        }
                    },
                    {
                        "fraction": {
                            "value": 70.0,
                            "unit": "%",
                            "unit_type": "volumefraction"
                        },
                        "vapor_temp": {
                            "value": 231.44,
                            "unit": "C",
                            "unit_type": "temperature"
                        }
                    },
                    {
                        "fraction": {
                            "value": 80.0,
                            "unit": "%",
                            "unit_type": "volumefraction"
                        },
                        "vapor_temp": {
                            "value": 237.66999999999996,
                            "unit": "C",
                            "unit_type": "temperature"
                        }
                    },
                    {
                        "fraction": {
                            "value": 90.0,
                            "unit": "%",
                            "unit_type": "volumefraction"
                        },
                        "vapor_temp": {
                            "value": 243.46000000000004,
                            "unit": "C",
                            "unit_type": "temperature"
                        }
                    },
                    {
                        "fraction": {
                            "value": 95.0,
                            "unit": "%",
                            "unit_type": "volumefraction"
                        },
                        "vapor_temp": {
                            "value": 246.22000000000003,
                            "unit": "C",
                            "unit_type": "temperature"
                        }
                    }
                ]
            },
            "bulk_composition": [
                {
                    "name": "Carbon Mass Fraction",
                    "measurement": {
                        "value": 85.83,
                        "unit": "%",
                        "unit_type": "massfraction"
                    }
                },
                {
                    "name": "Hydrogen Mass Fraction",
                    "measurement": {
                        "value": 13.83,
                        "unit": "%",
                        "unit_type": "massfraction"
                    }
                },
                {
                    "name": "Sulfur Mass Fraction",
                    "measurement": {
                        "value": 0.35516,
                        "unit": "%",
                        "unit_type": "massfraction"
                    }
                },
                {
                    "name": "Mercaptan Sulfur Mass Fraction",
                    "measurement": {
                        "value": 20.07,
                        "unit": "ppm",
                        "unit_type": "massfraction"
                    }
                },
                {
                    "name": "Nitrogen Mass Fraction",
                    "measurement": {
                        "value": 0.78729,
                        "unit": "ppm",
                        "unit_type": "massfraction"
                    }
                },
                {
                    "name": "Paraffin Volume Fraction",
                    "measurement": {
                        "value": 33.407,
                        "unit": "%",
                        "unit_type": "massfraction"
                    }
                },
                {
                    "name": "Naphthene Volume Fraction",
                    "measurement": {
                        "value": 51.309,
                        "unit": "%",
                        "unit_type": "massfraction"
                    }
                },
                {
                    "name": "Aromatics (FIA)",
                    "measurement": {
                        "value": 15.284,
                        "unit": "%",
                        "unit_type": "massfraction"
                    }
                },
                {
                    "name": "Naphthalene Volume Fraction",
                    "measurement": {
                        "value": 0.27188,
                        "unit": "%",
                        "unit_type": "massfraction"
                    }
                }
            ],
            "industry_properties": [
                {
                    "name": "Total Acid Number",
                    "measurement": {
                        "value": 0.16644,
                        "unit": "mg/g",
                        "unit_type": "massfraction"
                    }
                },
                {
                    "name": "Freeze Point",
                    "measurement": {
                        "value": -66.8812,
                        "unit": "F",
                        "unit_type": "temperature"
                    }
                },
                {
                    "name": "Smoke Point",
                    "measurement": {
                        "value": 24.0124,
                        "unit": "mm",
                        "unit_type": "length"
                    }
                },
                {
                    "name": "Cetane Index 1990 (D4737)",
                    "measurement": {
                        "value": 39.3023,
                        "unit_type": "unitless"
                    }
                },
                {
                    "name": "Cloud Point",
                    "measurement": {
                        "value": -76.5242,
                        "unit": "F",
                        "unit_type": "temperature"
                    }
                },
                {
                    "name": "Aniline Point",
                    "measurement": {
                        "value": 143.712,
                        "unit": "F",
                        "unit_type": "temperature"
                    }
                }
            ]
        },
        {
            "metadata": {
                "name": "Diesel 480 - 650F",
                "short_name": "Diesel 480 -...",
                "boiling_point_range": {
                    "unit": "F",
                    "min_value": 480.0,
                    "max_value": 650.0,
                    "unit_type": "temperature"
                }
            },
            "cut_volume": {
                "value": 11.2666,
                "unit": "%",
                "unit_type": "volumefraction"
            },
            "physical_properties": {
                "pour_point": {
                    "measurement": {
                        "value": -30.654381,
                        "unit": "C",
                        "unit_type": "temperature"
                    }
                },
                "densities": [
                    {
                        "density": {
                            "value": 0.89261,
                            "unit": "g/cm^3",
                            "unit_type": "density"
                        },
                        "ref_temp": {
                            "value": 15.6,
                            "unit": "C",
                            "unit_type": "temperature"
                        }
                    }
                ],
                "kinematic_viscosities": [
                    {
                        "viscosity": {
                            "value": 12.19,
                            "unit": "cSt",
                            "unit_type": "kinematicviscosity"
                        },
                        "ref_temp": {
                            "value": 20.0,
                            "unit": "C",
                            "unit_type": "temperature"
                        }
                    },
                    {
                        "viscosity": {
                            "value": 6.1932,
                            "unit": "cSt",
                            "unit_type": "kinematicviscosity"
                        },
                        "ref_temp": {
                            "value": 40.0,
                            "unit": "C",
                            "unit_type": "temperature"
                        }
                    },
                    {
                        "viscosity": {
                            "value": 4.7132,
                            "unit": "cSt",
                            "unit_type": "kinematicviscosity"
                        },
                        "ref_temp": {
                            "value": 50.0,
                            "unit": "C",
                            "unit_type": "temperature"
                        }
                    }
                ]
            },
            "distillation_data": {
                "type": "volume fraction",
                "end_point": {
                    "value": 342.97,
                    "unit": "C",
                    "unit_type": "temperature"
                },
                "fraction_recovered": {
                    "value": 1.0,
                    "unit": "fraction",
                    "unit_type": "concentration"
                },
                "cuts": [
                    {
                        "fraction": {
                            "value": 0.0,
                            "unit": "%",
                            "unit_type": "volumefraction"
                        },
                        "vapor_temp": {
                            "value": 249.60000000000002,
                            "unit": "C",
                            "unit_type": "temperature"
                        }
                    },
                    {
                        "fraction": {
                            "value": 5.0,
                            "unit": "%",
                            "unit_type": "volumefraction"
                        },
                        "vapor_temp": {
                            "value": 255.66999999999996,
                            "unit": "C",
                            "unit_type": "temperature"
                        }
                    },
                    {
                        "fraction": {
                            "value": 10.0,
                            "unit": "%",
                            "unit_type": "volumefraction"
                        },
                        "vapor_temp": {
                            "value": 261.98,
                            "unit": "C",
                            "unit_type": "temperature"
                        }
                    },
                    {
                        "fraction": {
                            "value": 20.0,
                            "unit": "%",
                            "unit_type": "volumefraction"
                        },
                        "vapor_temp": {
                            "value": 273.65,
                            "unit": "C",
                            "unit_type": "temperature"
                        }
                    },
                    {
                        "fraction": {
                            "value": 30.0,
                            "unit": "%",
                            "unit_type": "volumefraction"
                        },
                        "vapor_temp": {
                            "value": 284.30000000000007,
                            "unit": "C",
                            "unit_type": "temperature"
                        }
                    },
                    {
                        "fraction": {
                            "value": 40.0,
                            "unit": "%",
                            "unit_type": "volumefraction"
                        },
                        "vapor_temp": {
                            "value": 294.16999999999996,
                            "unit": "C",
                            "unit_type": "temperature"
                        }
                    },
                    {
                        "fraction": {
                            "value": 50.0,
                            "unit": "%",
                            "unit_type": "volumefraction"
                        },
                        "vapor_temp": {
                            "value": 303.40999999999997,
                            "unit": "C",
                            "unit_type": "temperature"
                        }
                    },
                    {
                        "fraction": {
                            "value": 60.0,
                            "unit": "%",
                            "unit_type": "volumefraction"
                        },
                        "vapor_temp": {
                            "value": 312.13,
                            "unit": "C",
                            "unit_type": "temperature"
                        }
                    },
                    {
                        "fraction": {
                            "value": 70.0,
                            "unit": "%",
                            "unit_type": "volumefraction"
                        },
                        "vapor_temp": {
                            "value": 320.41999999999996,
                            "unit": "C",
                            "unit_type": "temperature"
                        }
                    },
                    {
                        "fraction": {
                            "value": 80.0,
                            "unit": "%",
                            "unit_type": "volumefraction"
                        },
                        "vapor_temp": {
                            "value": 328.33000000000004,
                            "unit": "C",
                            "unit_type": "temperature"
                        }
                    },
                    {
                        "fraction": {
                            "value": 90.0,
                            "unit": "%",
                            "unit_type": "volumefraction"
                        },
                        "vapor_temp": {
                            "value": 335.94999999999993,
                            "unit": "C",
                            "unit_type": "temperature"
                        }
                    },
                    {
                        "fraction": {
                            "value": 95.0,
                            "unit": "%",
                            "unit_type": "volumefraction"
                        },
                        "vapor_temp": {
                            "value": 339.66999999999996,
                            "unit": "C",
                            "unit_type": "temperature"
                        }
                    }
                ]
            },
            "bulk_composition": [
                {
                    "name": "Carbon Mass Fraction",
                    "measurement": {
                        "value": 85.86,
                        "unit": "%",
                        "unit_type": "massfraction"
                    }
                },
                {
                    "name": "Hydrogen Mass Fraction",
                    "measurement": {
                        "value": 12.55,
                        "unit": "%",
                        "unit_type": "massfraction"
                    }
                },
                {
                    "name": "Sulfur Mass Fraction",
                    "measurement": {
                        "value": 1.5753,
                        "unit": "%",
                        "unit_type": "massfraction"
                    }
                },
                {
                    "name": "Mercaptan Sulfur Mass Fraction",
                    "measurement": {
                        "value": 19.26,
                        "unit": "ppm",
                        "unit_type": "massfraction"
                    }
                },
                {
                    "name": "Nitrogen Mass Fraction",
                    "measurement": {
                        "value": 74.671,
                        "unit": "ppm",
                        "unit_type": "massfraction"
                    }
                },
                {
                    "name": "Paraffin Volume Fraction",
                    "measurement": {
                        "value": 13.374,
                        "unit": "%",
                        "unit_type": "massfraction"
                    }
                },
                {
                    "name": "Naphthene Volume Fraction",
                    "measurement": {
                        "value": 52.401,
                        "unit": "%",
                        "unit_type": "massfraction"
                    }
                },
                {
                    "name": "Aromatics (FIA)",
                    "measurement": {
                        "value": 34.225,
                        "unit": "%",
                        "unit_type": "massfraction"
                    }
                },
                {
                    "name": "Naphthalene Volume Fraction",
                    "measurement": {
                        "value": 1.6458,
                        "unit": "%",
                        "unit_type": "massfraction"
                    }
                }
            ],
            "industry_properties": [
                {
                    "name": "Total Acid Number",
                    "measurement": {
                        "value": 1.3082,
                        "unit": "mg/g",
                        "unit_type": "massfraction"
                    }
                },
                {
                    "name": "Freeze Point",
                    "measurement": {
                        "value": -7.08241,
                        "unit": "F",
                        "unit_type": "temperature"
                    }
                },
                {
                    "name": "Smoke Point",
                    "measurement": {
                        "value": 14.7093,
                        "unit": "mm",
                        "unit_type": "length"
                    }
                },
                {
                    "name": "Cetane Index 1990 (D4737)",
                    "measurement": {
                        "value": 39.1714,
                        "unit_type": "unitless"
                    }
                },
                {
                    "name": "Cloud Point",
                    "measurement": {
                        "value": -21.148,
                        "unit": "F",
                        "unit_type": "temperature"
                    }
                },
                {
                    "name": "Aniline Point",
                    "measurement": {
                        "value": 139.954,
                        "unit": "F",
                        "unit_type": "temperature"
                    }
                }
            ]
        },
        {
            "metadata": {
                "name": "Vacuum Gas Oil 650 - 1000F",
                "short_name": "Vacuum Gas O...",
                "boiling_point_range": {
                    "unit": "F",
                    "min_value": 650.0,
                    "max_value": 1000.0,
                    "unit_type": "temperature"
                }
            },
            "cut_volume": {
                "value": 33.7107,
                "unit": "%",
                "unit_type": "volumefraction"
            },
            "physical_properties": {
                "pour_point": {
                    "measurement": {
                        "value": 7.4905193,
                        "unit": "C",
                        "unit_type": "temperature"
                    }
                },
                "densities": [
                    {
                        "density": {
                            "value": 0.97177,
                            "unit": "g/cm^3",
                            "unit_type": "density"
                        },
                        "ref_temp": {
                            "value": 15.6,
                            "unit": "C",
                            "unit_type": "temperature"
                        }
                    }
                ],
                "kinematic_viscosities": [
                    {
                        "viscosity": {
                            "value": 2387.7,
                            "unit": "cSt",
                            "unit_type": "kinematicviscosity"
                        },
                        "ref_temp": {
                            "value": 20.0,
                            "unit": "C",
                            "unit_type": "temperature"
                        }
                    },
                    {
                        "viscosity": {
                            "value": 371.27,
                            "unit": "cSt",
                            "unit_type": "kinematicviscosity"
                        },
                        "ref_temp": {
                            "value": 40.0,
                            "unit": "C",
                            "unit_type": "temperature"
                        }
                    },
                    {
                        "viscosity": {
                            "value": 179.96,
                            "unit": "cSt",
                            "unit_type": "kinematicviscosity"
                        },
                        "ref_temp": {
                            "value": 50.0,
                            "unit": "C",
                            "unit_type": "temperature"
                        }
                    }
                ]
            },
            "distillation_data": {
                "type": "volume fraction",
                "end_point": {
                    "value": 536.69,
                    "unit": "C",
                    "unit_type": "temperature"
                },
                "fraction_recovered": {
                    "value": 1.0,
                    "unit": "fraction",
                    "unit_type": "concentration"
                },
                "cuts": [
                    {
                        "fraction": {
                            "value": 0.0,
                            "unit": "%",
                            "unit_type": "volumefraction"
                        },
                        "vapor_temp": {
                            "value": 344.42999999999995,
                            "unit": "C",
                            "unit_type": "temperature"
                        }
                    },
                    {
                        "fraction": {
                            "value": 5.0,
                            "unit": "%",
                            "unit_type": "volumefraction"
                        },
                        "vapor_temp": {
                            "value": 354.09000000000003,
                            "unit": "C",
                            "unit_type": "temperature"
                        }
                    },
                    {
                        "fraction": {
                            "value": 10.0,
                            "unit": "%",
                            "unit_type": "volumefraction"
                        },
                        "vapor_temp": {
                            "value": 364.57000000000005,
                            "unit": "C",
                            "unit_type": "temperature"
                        }
                    },
                    {
                        "fraction": {
                            "value": 20.0,
                            "unit": "%",
                            "unit_type": "volumefraction"
                        },
                        "vapor_temp": {
                            "value": 384.47,
                            "unit": "C",
                            "unit_type": "temperature"
                        }
                    },
                    {
                        "fraction": {
                            "value": 30.0,
                            "unit": "%",
                            "unit_type": "volumefraction"
                        },
                        "vapor_temp": {
                            "value": 403.14,
                            "unit": "C",
                            "unit_type": "temperature"
                        }
                    },
                    {
                        "fraction": {
                            "value": 40.0,
                            "unit": "%",
                            "unit_type": "volumefraction"
                        },
                        "vapor_temp": {
                            "value": 421.1,
                            "unit": "C",
                            "unit_type": "temperature"
                        }
                    },
                    {
                        "fraction": {
                            "value": 50.0,
                            "unit": "%",
                            "unit_type": "volumefraction"
                        },
                        "vapor_temp": {
                            "value": 438.93999999999994,
                            "unit": "C",
                            "unit_type": "temperature"
                        }
                    },
                    {
                        "fraction": {
                            "value": 60.0,
                            "unit": "%",
                            "unit_type": "volumefraction"
                        },
                        "vapor_temp": {
                            "value": 457.17999999999995,
                            "unit": "C",
                            "unit_type": "temperature"
                        }
                    },
                    {
                        "fraction": {
                            "value": 70.0,
                            "unit": "%",
                            "unit_type": "volumefraction"
                        },
                        "vapor_temp": {
                            "value": 476.14,
                            "unit": "C",
                            "unit_type": "temperature"
                        }
                    },
                    {
                        "fraction": {
                            "value": 80.0,
                            "unit": "%",
                            "unit_type": "volumefraction"
                        },
                        "vapor_temp": {
                            "value": 495.9599999999999,
                            "unit": "C",
                            "unit_type": "temperature"
                        }
                    },
                    {
                        "fraction": {
                            "value": 90.0,
                            "unit": "%",
                            "unit_type": "volumefraction"
                        },
                        "vapor_temp": {
                            "value": 516.5,
                            "unit": "C",
                            "unit_type": "temperature"
                        }
                    },
                    {
                        "fraction": {
                            "value": 95.0,
                            "unit": "%",
                            "unit_type": "volumefraction"
                        },
                        "vapor_temp": {
                            "value": 527.04,
                            "unit": "C",
                            "unit_type": "temperature"
                        }
                    }
                ]
            },
            "bulk_composition": [
                {
                    "name": "Carbon Mass Fraction",
                    "measurement": {
                        "value": 84.72,
                        "unit": "%",
                        "unit_type": "massfraction"
                    }
                },
                {
                    "name": "Hydrogen Mass Fraction",
                    "measurement": {
                        "value": 11.35,
                        "unit": "%",
                        "unit_type": "massfraction"
                    }
                },
                {
                    "name": "Sulfur Mass Fraction",
                    "measurement": {
                        "value": 3.5489,
                        "unit": "%",
                        "unit_type": "massfraction"
                    }
                },
                {
                    "name": "Mercaptan Sulfur Mass Fraction",
                    "measurement": {
                        "value": 5.566,
                        "unit": "ppm",
                        "unit_type": "massfraction"
                    }
                },
                {
                    "name": "Nitrogen Mass Fraction",
                    "measurement": {
                        "value": 1749.9,
                        "unit": "ppm",
                        "unit_type": "massfraction"
                    }
                },
                {
                    "name": "N-Heptane Insolubles (C7 Asphaltenes)",
                    "measurement": {
                        "value": 0,
                        "unit": "%",
                        "unit_type": "massfraction"
                    }
                },
                {
                    "name": "Paraffin Volume Fraction",
                    "measurement": {
                        "value": 8.3193,
                        "unit": "%",
                        "unit_type": "massfraction"
                    }
                },
                {
                    "name": "Naphthene Volume Fraction",
                    "measurement": {
                        "value": 28.457,
                        "unit": "%",
                        "unit_type": "massfraction"
                    }
                },
                {
                    "name": "Aromatics (FIA)",
                    "measurement": {
                        "value": 63.223,
                        "unit": "%",
                        "unit_type": "massfraction"
                    }
                }
            ],
            "industry_properties": [
                {
                    "name": "Total Acid Number",
                    "measurement": {
                        "value": 3.4989,
                        "unit": "mg/g",
                        "unit_type": "massfraction"
                    }
                },
                {
                    "name": "Conradson Carbon Residue",
                    "measurement": {
                        "value": 0.56012,
                        "unit": "%",
                        "unit_type": "massfraction"
                    }
                },
                {
                    "name": "Aniline Point",
                    "measurement": {
                        "value": 132.28,
                        "unit": "F",
                        "unit_type": "temperature"
                    }
                }
            ]
        },
        {
            "metadata": {
                "name": "Vacuum Residue 1000F+",
                "short_name": "Vacuum Resid...",
                "boiling_point_range": {
                    "unit": "F",
                    "min_value": 1000.0,
                    "unit_type": "temperature"
                }
            },
            "cut_volume": {
                "value": 32.7597,
                "unit": "%",
                "unit_type": "volumefraction"
            },
            "physical_properties": {
                "pour_point": {
                    "measurement": {
                        "value": 54.503341,
                        "unit": "C",
                        "unit_type": "temperature"
                    }
                },
                "densities": [
                    {
                        "density": {
                            "value": 1.049,
                            "unit": "g/cm^3",
                            "unit_type": "density"
                        },
                        "ref_temp": {
                            "value": 15.6,
                            "unit": "C",
                            "unit_type": "temperature"
                        }
                    }
                ],
                "kinematic_viscosities": [
                    {
                        "viscosity": {
                            "value": 127640000000.0,
                            "unit": "cSt",
                            "unit_type": "kinematicviscosity"
                        },
                        "ref_temp": {
                            "value": 20.0,
                            "unit": "C",
                            "unit_type": "temperature"
                        }
                    },
                    {
                        "viscosity": {
                            "value": 738720000.0,
                            "unit": "cSt",
                            "unit_type": "kinematicviscosity"
                        },
                        "ref_temp": {
                            "value": 40.0,
                            "unit": "C",
                            "unit_type": "temperature"
                        }
                    },
                    {
                        "viscosity": {
                            "value": 92748000.0,
                            "unit": "cSt",
                            "unit_type": "kinematicviscosity"
                        },
                        "ref_temp": {
                            "value": 50.0,
                            "unit": "C",
                            "unit_type": "temperature"
                        }
                    }
                ]
            },
            "distillation_data": {
                "type": "volume fraction",
                "end_point": {
                    "value": 824.92,
                    "unit": "C",
                    "unit_type": "temperature"
                },
                "fraction_recovered": {
                    "value": 1.0,
                    "unit": "fraction",
                    "unit_type": "concentration"
                },
                "cuts": [
                    {
                        "fraction": {
                            "value": 0.0,
                            "unit": "%",
                            "unit_type": "volumefraction"
                        },
                        "vapor_temp": {
                            "value": 538.83,
                            "unit": "C",
                            "unit_type": "temperature"
                        }
                    },
                    {
                        "fraction": {
                            "value": 5.0,
                            "unit": "%",
                            "unit_type": "volumefraction"
                        },
                        "vapor_temp": {
                            "value": 548.41,
                            "unit": "C",
                            "unit_type": "temperature"
                        }
                    },
                    {
                        "fraction": {
                            "value": 10.0,
                            "unit": "%",
                            "unit_type": "volumefraction"
                        },
                        "vapor_temp": {
                            "value": 559.26,
                            "unit": "C",
                            "unit_type": "temperature"
                        }
                    },
                    {
                        "fraction": {
                            "value": 20.0,
                            "unit": "%",
                            "unit_type": "volumefraction"
                        },
                        "vapor_temp": {
                            "value": 581.64,
                            "unit": "C",
                            "unit_type": "temperature"
                        }
                    },
                    {
                        "fraction": {
                            "value": 30.0,
                            "unit": "%",
                            "unit_type": "volumefraction"
                        },
                        "vapor_temp": {
                            "value": 605.01,
                            "unit": "C",
                            "unit_type": "temperature"
                        }
                    },
                    {
                        "fraction": {
                            "value": 40.0,
                            "unit": "%",
                            "unit_type": "volumefraction"
                        },
                        "vapor_temp": {
                            "value": 629.47,
                            "unit": "C",
                            "unit_type": "temperature"
                        }
                    },
                    {
                        "fraction": {
                            "value": 50.0,
                            "unit": "%",
                            "unit_type": "volumefraction"
                        },
                        "vapor_temp": {
                            "value": 655.08,
                            "unit": "C",
                            "unit_type": "temperature"
                        }
                    },
                    {
                        "fraction": {
                            "value": 60.0,
                            "unit": "%",
                            "unit_type": "volumefraction"
                        },
                        "vapor_temp": {
                            "value": 681.99,
                            "unit": "C",
                            "unit_type": "temperature"
                        }
                    },
                    {
                        "fraction": {
                            "value": 70.0,
                            "unit": "%",
                            "unit_type": "volumefraction"
                        },
                        "vapor_temp": {
                            "value": 710.45,
                            "unit": "C",
                            "unit_type": "temperature"
                        }
                    },
                    {
                        "fraction": {
                            "value": 80.0,
                            "unit": "%",
                            "unit_type": "volumefraction"
                        },
                        "vapor_temp": {
                            "value": 740.88,
                            "unit": "C",
                            "unit_type": "temperature"
                        }
                    },
                    {
                        "fraction": {
                            "value": 90.0,
                            "unit": "%",
                            "unit_type": "volumefraction"
                        },
                        "vapor_temp": {
                            "value": 773.9899999999999,
                            "unit": "C",
                            "unit_type": "temperature"
                        }
                    },
                    {
                        "fraction": {
                            "value": 95.0,
                            "unit": "%",
                            "unit_type": "volumefraction"
                        },
                        "vapor_temp": {
                            "value": 792.9600000000002,
                            "unit": "C",
                            "unit_type": "temperature"
                        }
                    }
                ]
            },
            "bulk_composition": [
                {
                    "name": "Carbon Mass Fraction",
                    "measurement": {
                        "value": 83.77,
                        "unit": "%",
                        "unit_type": "massfraction"
                    }
                },
                {
                    "name": "Hydrogen Mass Fraction",
                    "measurement": {
                        "value": 11.12,
                        "unit": "%",
                        "unit_type": "massfraction"
                    }
                },
                {
                    "name": "Sulfur Mass Fraction",
                    "measurement": {
                        "value": 6.5072,
                        "unit": "%",
                        "unit_type": "massfraction"
                    }
                },
                {
                    "name": "Mercaptan Sulfur Mass Fraction",
                    "measurement": {
                        "value": 0.3954,
                        "unit": "ppm",
                        "unit_type": "massfraction"
                    }
                },
                {
                    "name": "Nitrogen Mass Fraction",
                    "measurement": {
                        "value": 6829.6,
                        "unit": "ppm",
                        "unit_type": "massfraction"
                    }
                },
                {
                    "name": "N-Heptane Insolubles (C7 Asphaltenes)",
                    "measurement": {
                        "value": 9.892,
                        "unit": "%",
                        "unit_type": "massfraction"
                    }
                },
                {
                    "name": "Nickel Mass Fraction",
                    "measurement": {
                        "value": 136.91,
                        "unit": "ppm",
                        "unit_type": "massfraction"
                    }
                },
                {
                    "name": "Vanadium Mass Fraction",
                    "measurement": {
                        "value": 362.41,
                        "unit": "ppm",
                        "unit_type": "massfraction"
                    }
                },
                {
                    "name": "Paraffin Volume Fraction",
                    "measurement": {
                        "value": 0.44985,
                        "unit": "%",
                        "unit_type": "massfraction"
                    }
                },
                {
                    "name": "Naphthene Volume Fraction",
                    "measurement": {
                        "value": 4.9938,
                        "unit": "%",
                        "unit_type": "massfraction"
                    }
                },
                {
                    "name": "Aromatics (FIA)",
                    "measurement": {
                        "value": 94.556,
                        "unit": "%",
                        "unit_type": "massfraction"
                    }
                }
            ],
            "industry_properties": [
                {
                    "name": "Total Acid Number",
                    "measurement": {
                        "value": 1.8007,
                        "unit": "mg/g",
                        "unit_type": "massfraction"
                    }
                },
                {
                    "name": "Conradson Carbon Residue",
                    "measurement": {
                        "value": 24.014,
                        "unit": "%",
                        "unit_type": "massfraction"
                    }
                }
            ]
        }
    ]
}