{
    "oil_id": "AD01824",
    "adios_data_model_version": "0.11.0",
    "metadata": {
        "name": "GRIFFIN, BHP PETROLEUM",
        "source_id": "AD01824",
        "reference": {
            "year": 1998,
            "reference": "Gilbert, T., Austrlian Maritime Safety Authority., Letter to William Lehr, NOAA, February 26, 1998."
        },
        "product_type": "Crude Oil NOS",
        "API": 55.0,
        "labels": [
            "Light Crude",
            "Crude Oil"
        ],
        "model_completeness": 43,
        "gnome_suitable": true
    },
    "sub_samples": [
        {
            "metadata": {
                "name": "Fresh Oil Sample",
                "short_name": "Fresh Oil",
                "fraction_evaporated": {
                    "value": 0.0,
                    "unit": "fraction",
                    "unit_type": "massfraction"
                }
            },
            "physical_properties": {
                "pour_point": {
                    "measurement": {
                        "value": -48,
                        "unit": "C",
                        "unit_type": "temperature"
                    }
                },
                "densities": [
                    {
                        "density": {
                            "value": 759.0,
                            "unit": "kg/m^3",
                            "unit_type": "density"
                        },
                        "ref_temp": {
                            "value": 16,
                            "unit": "C",
                            "unit_type": "temperature"
                        }
                    }
                ],
                "kinematic_viscosities": [
                    {
                        "viscosity": {
                            "value": 1.24e-06,
                            "unit": "m^2/s",
                            "unit_type": "kinematicviscosity"
                        },
                        "ref_temp": {
                            "value": 20,
                            "unit": "C",
                            "unit_type": "temperature"
                        }
                    }
                ]
            },
            "distillation_data": {
                "type": "volume fraction",
                "cuts": [
                    {
                        "fraction": {
                            "value": 0.033,
                            "unit": "fraction",
                            "unit_type": "volumefraction"
                        },
                        "vapor_temp": {
                            "value": 22.0,
                            "unit": "C",
                            "unit_type": "temperature"
                        }
                    },
                    {
                        "fraction": {
                            "value": 0.119,
                            "unit": "fraction",
                            "unit_type": "volumefraction"
                        },
                        "vapor_temp": {
                            "value": 70.0,
                            "unit": "C",
                            "unit_type": "temperature"
                        }
                    },
                    {
                        "fraction": {
                            "value": 0.244,
                            "unit": "fraction",
                            "unit_type": "volumefraction"
                        },
                        "vapor_temp": {
                            "value": 100.0,
                            "unit": "C",
                            "unit_type": "temperature"
                        }
                    },
                    {
                        "fraction": {
                            "value": 0.334,
                            "unit": "fraction",
                            "unit_type": "volumefraction"
                        },
                        "vapor_temp": {
                            "value": 120.0,
                            "unit": "C",
                            "unit_type": "temperature"
                        }
                    },
                    {
                        "fraction": {
                            "value": 0.421,
                            "unit": "fraction",
                            "unit_type": "volumefraction"
                        },
                        "vapor_temp": {
                            "value": 135.0,
                            "unit": "C",
                            "unit_type": "temperature"
                        }
                    },
                    {
                        "fraction": {
                            "value": 0.529,
                            "unit": "fraction",
                            "unit_type": "volumefraction"
                        },
                        "vapor_temp": {
                            "value": 160.0,
                            "unit": "C",
                            "unit_type": "temperature"
                        }
                    },
                    {
                        "fraction": {
                            "value": 0.605,
                            "unit": "fraction",
                            "unit_type": "volumefraction"
                        },
                        "vapor_temp": {
                            "value": 180.0,
                            "unit": "C",
                            "unit_type": "temperature"
                        }
                    },
                    {
                        "fraction": {
                            "value": 0.718,
                            "unit": "fraction",
                            "unit_type": "volumefraction"
                        },
                        "vapor_temp": {
                            "value": 220.0,
                            "unit": "C",
                            "unit_type": "temperature"
                        }
                    },
                    {
                        "fraction": {
                            "value": 0.801,
                            "unit": "fraction",
                            "unit_type": "volumefraction"
                        },
                        "vapor_temp": {
                            "value": 260.0,
                            "unit": "C",
                            "unit_type": "temperature"
                        }
                    },
                    {
                        "fraction": {
                            "value": 0.907,
                            "unit": "fraction",
                            "unit_type": "volumefraction"
                        },
                        "vapor_temp": {
                            "value": 330.0,
                            "unit": "C",
                            "unit_type": "temperature"
                        }
                    },
                    {
                        "fraction": {
                            "value": 0.965,
                            "unit": "fraction",
                            "unit_type": "volumefraction"
                        },
                        "vapor_temp": {
                            "value": 400.0,
                            "unit": "C",
                            "unit_type": "temperature"
                        }
                    }
                ]
            },
            "bulk_composition": [
                {
                    "name": "wax_content",
                    "measurement": {
                        "value": 0.007,
                        "unit": "fraction",
                        "unit_type": "massfraction"
                    }
                }
            ]
        }
    ],
    "status": [
        "W009: Distillation fraction recovered is missing or invalid",
        "E043: API, 55.0 does not match density at 60F. API should be: 54.8"
    ]
}