{
    "oil_id": "AD01424",
    "adios_data_model_version": "0.12.0",
    "metadata": {
        "name": "KABINDA, GALLAGER MARINE",
        "source_id": "AD01424",
        "location": "Angola",
        "reference": {
            "year": 2017,
            "reference": "13-May-96"
        },
        "product_type": "Crude Oil NOS",
        "API": 32.9,
        "labels": [
            "Crude Oil",
            "Medium Crude"
        ],
        "model_completeness": 40,
        "gnome_suitable": true,
        "change_log": [
            {
                "name": "R",
                "date": "2022-11-25T14:21:39.049-08:00",
                "comment": "Issue #27 - Normalize Location"
            }
        ]
    },
    "sub_samples": [
        {
            "metadata": {
                "name": "Fresh Oil Sample",
                "short_name": "Fresh Oil",
                "fraction_evaporated": {
                    "value": 0.0,
                    "unit": "fraction",
                    "unit_type": "massfraction"
                }
            },
            "physical_properties": {
                "pour_point": {
                    "measurement": {
                        "unit": "C",
                        "min_value": -6.0,
                        "max_value": 18.0,
                        "unit_type": "temperature"
                    }
                },
                "densities": [
                    {
                        "density": {
                            "value": 859.96,
                            "unit": "kg/m^3",
                            "unit_type": "density"
                        },
                        "ref_temp": {
                            "value": 288.16,
                            "unit": "K",
                            "unit_type": "temperature"
                        },
                        "method": "Converted from API"
                    }
                ],
                "kinematic_viscosities": [
                    {
                        "viscosity": {
                            "value": 3.9e-05,
                            "unit": "m^2/s",
                            "unit_type": "kinematicviscosity"
                        },
                        "ref_temp": {
                            "value": 20.0,
                            "unit": "C",
                            "unit_type": "temperature"
                        }
                    }
                ]
            },
            "distillation_data": {
                "type": "volume fraction",
                "cuts": [
                    {
                        "fraction": {
                            "value": 0.076,
                            "unit": "fraction",
                            "unit_type": "volumefraction"
                        },
                        "vapor_temp": {
                            "value": 100.0,
                            "unit": "C",
                            "unit_type": "temperature"
                        }
                    },
                    {
                        "fraction": {
                            "value": 0.203,
                            "unit": "fraction",
                            "unit_type": "volumefraction"
                        },
                        "vapor_temp": {
                            "value": 200.0,
                            "unit": "C",
                            "unit_type": "temperature"
                        }
                    },
                    {
                        "fraction": {
                            "value": 0.354,
                            "unit": "fraction",
                            "unit_type": "volumefraction"
                        },
                        "vapor_temp": {
                            "value": 300.0,
                            "unit": "C",
                            "unit_type": "temperature"
                        }
                    },
                    {
                        "fraction": {
                            "value": 0.468,
                            "unit": "fraction",
                            "unit_type": "volumefraction"
                        },
                        "vapor_temp": {
                            "value": 370.0,
                            "unit": "C",
                            "unit_type": "temperature"
                        }
                    }
                ]
            }
        }
    ],
    "status": [
        "W009: Distillation fraction recovered is missing or invalid"
    ],
    "review_status": {
        "status": "Not Reviewed"
    }
}