{
    "oil_id": "AD01855",
    "adios_data_model_version": "0.11.0",
    "metadata": {
        "name": "BLINA, BP",
        "source_id": "AD01855",
        "location": "AUSTRALIA",
        "reference": {
            "year": 1998,
            "reference": "Gilbert, T., Austrlian Maritime Safety Authority., Letter to William Lehr, NOAA, March 24, 1998."
        },
        "product_type": "Crude Oil NOS",
        "API": 35.5,
        "labels": [
            "Light Crude",
            "Crude Oil"
        ],
        "model_completeness": 32,
        "gnome_suitable": true
    },
    "sub_samples": [
        {
            "metadata": {
                "name": "Fresh Oil Sample",
                "short_name": "Fresh Oil",
                "fraction_evaporated": {
                    "value": 0.0,
                    "unit": "fraction",
                    "unit_type": "massfraction"
                }
            },
            "physical_properties": {
                "pour_point": {
                    "measurement": {
                        "value": 6.0,
                        "unit": "C",
                        "unit_type": "temperature"
                    }
                },
                "densities": [
                    {
                        "density": {
                            "value": 847.0,
                            "unit": "kg/m^3",
                            "unit_type": "density"
                        },
                        "ref_temp": {
                            "value": 15.0,
                            "unit": "C",
                            "unit_type": "temperature"
                        }
                    }
                ],
                "kinematic_viscosities": [
                    {
                        "viscosity": {
                            "value": 6.39e-06,
                            "unit": "m^2/s",
                            "unit_type": "kinematicviscosity"
                        },
                        "ref_temp": {
                            "value": 40.0,
                            "unit": "C",
                            "unit_type": "temperature"
                        }
                    },
                    {
                        "viscosity": {
                            "value": 5.02e-06,
                            "unit": "m^2/s",
                            "unit_type": "kinematicviscosity"
                        },
                        "ref_temp": {
                            "value": 50.0,
                            "unit": "C",
                            "unit_type": "temperature"
                        }
                    },
                    {
                        "viscosity": {
                            "value": 4.02e-06,
                            "unit": "m^2/s",
                            "unit_type": "kinematicviscosity"
                        },
                        "ref_temp": {
                            "value": 60.0,
                            "unit": "C",
                            "unit_type": "temperature"
                        }
                    }
                ]
            },
            "SARA": {
                "asphaltenes": {
                    "value": 0.0025,
                    "unit": "fraction",
                    "unit_type": "massfraction"
                }
            },
            "distillation_data": {
                "type": "volume fraction",
                "cuts": [
                    {
                        "fraction": {
                            "value": 0.134,
                            "unit": "fraction",
                            "unit_type": "volumefraction"
                        },
                        "vapor_temp": {
                            "value": 149.0,
                            "unit": "C",
                            "unit_type": "temperature"
                        }
                    },
                    {
                        "fraction": {
                            "value": 0.305,
                            "unit": "fraction",
                            "unit_type": "volumefraction"
                        },
                        "vapor_temp": {
                            "value": 232.0,
                            "unit": "C",
                            "unit_type": "temperature"
                        }
                    },
                    {
                        "fraction": {
                            "value": 0.547,
                            "unit": "fraction",
                            "unit_type": "volumefraction"
                        },
                        "vapor_temp": {
                            "value": 342.0,
                            "unit": "C",
                            "unit_type": "temperature"
                        }
                    }
                ]
            }
        }
    ],
    "status": [
        "W009: Distillation fraction recovered is missing or invalid"
    ],
    "review_status": {
        "status": "Not Reviewed"
    }
}